{
  "TimeChart": [
    {
      "Day": "Friday",
      "Schedule": [
        {
          "Time": "06:00",
          "Activity": "Drink Oil",
          "Comment": "Krithiga\n--------\nGingily oil 1 small tsp"
        },
        {
          "Time": "06:05",
          "Activity": "Yoga",
          "Comment": ""
        },
        {
          "Time": "07:00",
          "Activity": "Day starter vegetable",
          "Comment": "Hariprasad\n----------\nSmall Bitter gourd - 1"
        },
        {
          "Time": "08:00",
          "Activity": "Fruits",
          "Comment": "Common\n------\nHalf pomegranate each"
        },
        {
          "Time": "08:50",
          "Activity": "Drink Ghee",
          "Comment": "Krithiga\n--------\nCow ghee 1 tsp"
        },
        {
          "Time": "09:00",
          "Activity": "Breakfast",
          "Comment": "Krithiga\n--------\nSoaked sprouts\nBadam - 10\nWalnut - 3\nPista - 4\nGround nut - 2 tsp\nPumpkin seeds - 1 tsp\nsunflower seed - 1 tsp\n\nHariprasad\n----------\nSoaked sprouts\nBadam - 10\nWalnut - 3\nPista - 4\nGround nut - 2 tsp\nPumpkin seeds - 1 tsp\n\nCommon\n------\nVegetable salad\nEgg"
        },
        {
          "Time": "10:00",
          "Activity": "Vegetable Juice",
          "Comment": "Common\n------\nKothavarai juice with 40 pieces\n1 glass each."
        },
        {
          "Time": "10:30",
          "Activity": "Medicinal Drink",
          "Comment": "Krithiga\n--------\nAvarampoo decoction - 1tsp in 1 glass\n\nHariprasad\n----------\nManjal karisalankanni decoction - 1tsp in 1 glass"
        },
        {
          "Time": "11:00",
          "Activity": "Detox Drink",
          "Comment": "Common\n------\nAmla and curry leaves juice with butter milk"
        },
        {
          "Time": "12:00",
          "Activity": "Lemon",
          "Comment": "Common\n------\nSmall lemon 1 each"
        },
        {
          "Time": "13:30",
          "Activity": "Lunch",
          "Comment": "Common\n------\nKeerai (manathakali)"
        },
        {
          "Time": "13:45",
          "Activity": "Vegetable Raita",
          "Comment": "Common\n------\nRidge gourd\nAsh gourd\nBottle gourd\nSnake Gourd\nKovakkai\nChow-Chow"
        },
        {
          "Time": "15:30",
          "Activity": "Energy Drink",
          "Comment": "Krithiga\n--------\nHalf glass coconut milk"
        },
        {
          "Time": "17:00",
          "Activity": "Fruits",
          "Comment": "Common\n------\nInclude Raw Guava / Athikkai"
        },
        {
          "Time": "19:30",
          "Activity": "Tub bath",
          "Comment": "Krithiga\n--------\nTub bath with cold water"
        },
        {
          "Time": "19:45",
          "Activity": "Tub bath",
          "Comment": "Hariprasad\n----------\nTub bath with cold water"
        },
        {
          "Time": "20:00",
          "Activity": "Dinner",
          "Comment": "Common\n------\nTiffen"
        },
        {
          "Time": "20:45",
          "Activity": "Walking",
          "Comment": ""
        },
        {
          "Time": "20:55",
          "Activity": "Finisher Drink",
          "Comment": "Krithiga\n--------\nBadam pisin"
        },
        {
          "Time": "21:00",
          "Activity": "Prepare for next day",
          "Comment": "Common\n------\nSoak nuts\nOrder essentials\nSoak badam pisin"
        },
        {
          "Time": "21:15",
          "Activity": "Medicine",
          "Comment": "Hariprasad\n----------\nAshwaganda chooranam\nPaternia XT"
        }
      ]
    },
    {
      "Day": "Monday",
      "Schedule": [
        {
          "Time": "06:00",
          "Activity": "Drink Oil",
          "Comment": "Krithiga\n--------\nGingily oil 1 small tsp"
        },
        {
          "Time": "06:05",
          "Activity": "Yoga",
          "Comment": ""
        },
        {
          "Time": "07:00",
          "Activity": "Day starter vegetable",
          "Comment": "Hariprasad\n----------\nSmall Bitter gourd - 1"
        },
        {
          "Time": "08:00",
          "Activity": "Fruits",
          "Comment": "Common\n------\nHalf pomegranate each"
        },
        {
          "Time": "08:50",
          "Activity": "Drink Ghee",
          "Comment": "Krithiga\n--------\nCow ghee 1 tsp"
        },
        {
          "Time": "09:00",
          "Activity": "Breakfast",
          "Comment": "Krithiga\n--------\nSoaked sprouts\nBadam - 10\nWalnut - 3\nPista - 4\nGround nut - 2 tsp\nPumpkin seeds - 1 tsp\nsunflower seed - 1 tsp\n\nHariprasad\n----------\nSoaked sprouts\nBadam - 10\nWalnut - 3\nPista - 4\nGround nut - 2 tsp\nPumpkin seeds - 1 tsp"
        },
        {
          "Time": "10:00",
          "Activity": "Vegetable Juice",
          "Comment": "Common\n------\nKothavarai juice with 40 pieces\n1 glass each."
        },
        {
          "Time": "10:30",
          "Activity": "Medicinal Drink",
          "Comment": "Krithiga\n--------\nAvarampoo decoction - 1tsp in 1 glass\n\nHariprasad\n----------\nManjal karisalankanni decoction - 1tsp in 1 glass"
        },
        {
          "Time": "11:00",
          "Activity": "Detox Drink",
          "Comment": "Common\n------\nAmla and curry leaves juice with butter milk"
        },
        {
          "Time": "12:00",
          "Activity": "Lemon",
          "Comment": "Common\n------\nSmall lemon 1 each"
        },
        {
          "Time": "13:30",
          "Activity": "Lunch",
          "Comment": "Common\n------\nVazhapoo poriyal\nDrumstick"
        },
        {
          "Time": "13:45",
          "Activity": "Vegetable Raita",
          "Comment": "Common\n------\nRidge gourd\nAsh gourd\nBottle gourd\nSnake Gourd\nKovakkai\nChow-Chow"
        },
        {
          "Time": "15:30",
          "Activity": "Energy Drink",
          "Comment": "Krithiga\n--------\nHalf glass coconut milk"
        },
        {
          "Time": "17:00",
          "Activity": "Fruits",
          "Comment": "Common\n------\nInclude Raw Guava / Athikkai"
        },
        {
          "Time": "19:30",
          "Activity": "Tub bath",
          "Comment": "Krithiga\n--------\nTub bath with cold water"
        },
        {
          "Time": "19:45",
          "Activity": "Tub bath",
          "Comment": "Hariprasad\n----------\nTub bath with cold water"
        },
        {
          "Time": "20:00",
          "Activity": "Dinner",
          "Comment": "Common\n------\nTiffen"
        },
        {
          "Time": "20:45",
          "Activity": "Walking",
          "Comment": ""
        },
        {
          "Time": "20:55",
          "Activity": "Finisher Drink",
          "Comment": "Krithiga\n--------\nBadam pisin"
        },
        {
          "Time": "21:00",
          "Activity": "Prepare for next day",
          "Comment": "Common\n------\nSoak nuts\nOrder essentials\nSoak badam pisin"
        },
        {
          "Time": "21:15",
          "Activity": "Medicine",
          "Comment": "Hariprasad\n----------\nAshwaganda chooranam\nPaternia XT"
        }
      ]
    },
    {
      "Day": "Saturday",
      "Schedule": [
        {
          "Time": "06:00",
          "Activity": "Drink Oil",
          "Comment": "Krithiga\n--------\nGingily oil 1 small tsp"
        },
        {
          "Time": "06:05",
          "Activity": "Yoga",
          "Comment": ""
        },
        {
          "Time": "07:00",
          "Activity": "Day starter vegetable",
          "Comment": "Hariprasad\n----------\nAvarakkai - 8"
        },
        {
          "Time": "08:00",
          "Activity": "Fruits",
          "Comment": "Common\n------\nHalf pomegranate each"
        },
        {
          "Time": "08:50",
          "Activity": "Drink Ghee",
          "Comment": "Krithiga\n--------\nCow ghee 1 tsp"
        },
        {
          "Time": "09:00",
          "Activity": "Breakfast",
          "Comment": "Krithiga\n--------\nSoaked sprouts\nBadam - 10\nWalnut - 3\nPista - 4\nGround nut - 2 tsp\nPumpkin seeds - 1 tsp\nsunflower seed - 1 tsp\n\nHariprasad\n----------\nSoaked sprouts\nBadam - 10\nWalnut - 3\nPista - 4\nGround nut - 2 tsp\nPumpkin seeds - 1 tsp"
        },
        {
          "Time": "10:00",
          "Activity": "Vegetable Juice",
          "Comment": "Common\n------\nKothavarai juice with 40 pieces\n1 glass each."
        },
        {
          "Time": "10:30",
          "Activity": "Medicinal Drink",
          "Comment": "Krithiga\n--------\nAvarampoo decoction - 1tsp in 1 glass\n\nHariprasad\n----------\nManjal karisalankanni decoction - 1tsp in 1 glass"
        },
        {
          "Time": "11:00",
          "Activity": "Detox Drink",
          "Comment": "Common\n------\nAmla and curry leaves juice with butter milk"
        },
        {
          "Time": "12:00",
          "Activity": "Lemon",
          "Comment": "Common\n------\nSmall lemon 1 each"
        },
        {
          "Time": "13:30",
          "Activity": "Lunch",
          "Comment": "Common\n------\nKeerai (manathakali)"
        },
        {
          "Time": "13:45",
          "Activity": "Vegetable Raita",
          "Comment": "Common\n------\nRidge gourd\nAsh gourd\nBottle gourd\nSnake Gourd\nKovakkai\nChow-Chow"
        },
        {
          "Time": "15:30",
          "Activity": "Energy Drink",
          "Comment": "Krithiga\n--------\nHalf glass coconut milk"
        },
        {
          "Time": "17:00",
          "Activity": "Fruits",
          "Comment": "Common\n------\nAny fruits"
        },
        {
          "Time": "19:30",
          "Activity": "Tub bath",
          "Comment": "Krithiga\n--------\nTub bath with cold water"
        },
        {
          "Time": "19:45",
          "Activity": "Tub bath",
          "Comment": "Hariprasad\n----------\nTub bath with cold water"
        },
        {
          "Time": "20:00",
          "Activity": "Dinner",
          "Comment": "Common\n------\nTiffen"
        },
        {
          "Time": "20:45",
          "Activity": "Walking",
          "Comment": ""
        },
        {
          "Time": "20:55",
          "Activity": "Finisher Drink",
          "Comment": "Krithiga\n--------\nBadam pisin"
        },
        {
          "Time": "21:00",
          "Activity": "Prepare for next day",
          "Comment": "Common\n------\nSoak nuts\nOrder essentials\nSoak badam pisin"
        },
        {
          "Time": "21:15",
          "Activity": "Medicine",
          "Comment": "Hariprasad\n----------\nAshwaganda chooranam\nPaternia XT"
        }
      ]
    },
    {
      "Day": "Sunday",
      "Schedule": [
        {
          "Time": "06:00",
          "Activity": "Drink Oil",
          "Comment": "Krithiga\n--------\nGingily oil 1 small tsp"
        },
        {
          "Time": "06:05",
          "Activity": "Yoga",
          "Comment": ""
        },
        {
          "Time": "07:00",
          "Activity": "Day starter vegetable",
          "Comment": "Hariprasad\n----------\nAvarakkai - 8"
        },
        {
          "Time": "08:00",
          "Activity": "Fruits",
          "Comment": "Common\n------\nHalf pomegranate each"
        },
        {
          "Time": "08:50",
          "Activity": "Drink Ghee",
          "Comment": "Krithiga\n--------\nCow ghee 1 tsp"
        },
        {
          "Time": "09:00",
          "Activity": "Breakfast",
          "Comment": "Krithiga\n--------\nSoaked sprouts\nBadam - 10\nWalnut - 3\nPista - 4\nGround nut - 2 tsp\nPumpkin seeds - 1 tsp\nsunflower seed - 1 tsp\n\nHariprasad\n----------\nSoaked sprouts\nBadam - 10\nWalnut - 3\nPista - 4\nGround nut - 2 tsp\nPumpkin seeds - 1 tsp"
        },
        {
          "Time": "10:00",
          "Activity": "Vegetable Juice",
          "Comment": "Common\n------\nKothavarai juice with 40 pieces\n1 glass each."
        },
        {
          "Time": "10:30",
          "Activity": "Medicinal Drink",
          "Comment": "Krithiga\n--------\nAvarampoo decoction - 1tsp in 1 glass\n\nHariprasad\n----------\nManjal karisalankanni decoction - 1tsp in 1 glass"
        },
        {
          "Time": "11:00",
          "Activity": "Detox Drink",
          "Comment": "Common\n------\nAmla and curry leaves juice with butter milk"
        },
        {
          "Time": "12:00",
          "Activity": "Lemon",
          "Comment": "Common\n------\nSmall lemon 1 each"
        },
        {
          "Time": "13:30",
          "Activity": "Lunch",
          "Comment": "Common\n------\nKeerai (manathakali)"
        },
        {
          "Time": "13:45",
          "Activity": "Vegetable Raita",
          "Comment": "Common\n------\nRidge gourd\nAsh gourd\nBottle gourd\nSnake Gourd\nKovakkai\nChow-Chow"
        },
        {
          "Time": "15:30",
          "Activity": "Energy Drink",
          "Comment": "Krithiga\n--------\nHalf glass coconut milk"
        },
        {
          "Time": "17:00",
          "Activity": "Fruits",
          "Comment": "Common\n------\nAny fruits"
        },
        {
          "Time": "19:30",
          "Activity": "Tub bath",
          "Comment": "Krithiga\n--------\nTub bath with cold water"
        },
        {
          "Time": "19:45",
          "Activity": "Tub bath",
          "Comment": "Hariprasad\n----------\nTub bath with cold water"
        },
        {
          "Time": "20:00",
          "Activity": "Dinner",
          "Comment": "Common\n------\nTiffen"
        },
        {
          "Time": "20:45",
          "Activity": "Walking",
          "Comment": ""
        },
        {
          "Time": "20:55",
          "Activity": "Finisher Drink",
          "Comment": "Krithiga\n--------\nBadam pisin"
        },
        {
          "Time": "21:00",
          "Activity": "Prepare for next day",
          "Comment": "Common\n------\nSoak nuts\nOrder essentials\nSoak badam pisin"
        },
        {
          "Time": "21:15",
          "Activity": "Medicine",
          "Comment": "Hariprasad\n----------\nAshwaganda chooranam\nPaternia XT"
        }
      ]
    },
    {
      "Day": "Thursday",
      "Schedule": [
        {
          "Time": "06:00",
          "Activity": "Drink Oil",
          "Comment": "Krithiga\n--------\nGingily oil 1 small tsp"
        },
        {
          "Time": "06:05",
          "Activity": "Yoga",
          "Comment": ""
        },
        {
          "Time": "07:00",
          "Activity": "Day starter vegetable",
          "Comment": "Hariprasad\n----------\nBeans - 8"
        },
        {
          "Time": "08:00",
          "Activity": "Fruits",
          "Comment": "Common\n------\nHalf pomegranate each"
        },
        {
          "Time": "08:50",
          "Activity": "Drink Ghee",
          "Comment": "Krithiga\n--------\nCow ghee 1 tsp"
        },
        {
          "Time": "09:00",
          "Activity": "Breakfast",
          "Comment": "Krithiga\n--------\nSoaked sprouts\nBadam - 10\nWalnut - 3\nPista - 4\nGround nut - 2 tsp\nPumpkin seeds - 1 tsp\nsunflower seed - 1 tsp\n\nHariprasad\n----------\nSoaked sprouts\nBadam - 10\nWalnut - 3\nPista - 4\nGround nut - 2 tsp\nPumpkin seeds - 1 tsp\n\nCommon\n------\nPuttu with kadala kari"
        },
        {
          "Time": "10:00",
          "Activity": "Vegetable Juice",
          "Comment": "Common\n------\nKothavarai juice with 40 pieces\n1 glass each."
        },
        {
          "Time": "10:30",
          "Activity": "Medicinal Drink",
          "Comment": "Krithiga\n--------\nAvarampoo decoction - 1tsp in 1 glass\n\nHariprasad\n----------\nManjal karisalankanni decoction - 1tsp in 1 glass"
        },
        {
          "Time": "11:00",
          "Activity": "Detox Drink",
          "Comment": "Common\n------\nAmla and curry leaves juice with butter milk"
        },
        {
          "Time": "12:00",
          "Activity": "Lemon",
          "Comment": "Common\n------\nSmall lemon 1 each"
        },
        {
          "Time": "13:30",
          "Activity": "Lunch",
          "Comment": "Common\n------\nVazhapoo poriyal\nDrumstick"
        },
        {
          "Time": "13:45",
          "Activity": "Vegetable Raita",
          "Comment": "Common\n------\nRidge gourd\nAsh gourd\nBottle gourd\nSnake Gourd\nKovakkai\nChow-Chow"
        },
        {
          "Time": "15:30",
          "Activity": "Energy Drink",
          "Comment": "Krithiga\n--------\nHalf glass coconut milk"
        },
        {
          "Time": "17:00",
          "Activity": "Fruits",
          "Comment": "Common\n------\nAny fruits"
        },
        {
          "Time": "19:30",
          "Activity": "Tub bath",
          "Comment": "Krithiga\n--------\nTub bath with cold water"
        },
        {
          "Time": "19:45",
          "Activity": "Tub bath",
          "Comment": "Hariprasad\n----------\nTub bath with cold water"
        },
        {
          "Time": "20:00",
          "Activity": "Dinner",
          "Comment": "Common\n------\nTiffen"
        },
        {
          "Time": "20:45",
          "Activity": "Walking",
          "Comment": ""
        },
        {
          "Time": "20:55",
          "Activity": "Finisher Drink",
          "Comment": "Krithiga\n--------\nBadam pisin"
        },
        {
          "Time": "21:00",
          "Activity": "Prepare for next day",
          "Comment": "Common\n------\nSoak nuts\nOrder essentials\nSoak badam pisin"
        },
        {
          "Time": "21:15",
          "Activity": "Medicine",
          "Comment": "Hariprasad\n----------\nAshwaganda chooranam\nPaternia XT"
        }
      ]
    },
    {
      "Day": "Tuesday",
      "Schedule": [
        {
          "Time": "06:00",
          "Activity": "Drink Oil",
          "Comment": "Krithiga\n--------\nGingily oil 1 small tsp"
        },
        {
          "Time": "06:05",
          "Activity": "Yoga",
          "Comment": ""
        },
        {
          "Time": "07:00",
          "Activity": "Day starter vegetable",
          "Comment": "Hariprasad\n----------\nBeans - 8"
        },
        {
          "Time": "08:00",
          "Activity": "Fruits",
          "Comment": "Common\n------\nHalf pomegranate each"
        },
        {
          "Time": "08:50",
          "Activity": "Drink Ghee",
          "Comment": "Krithiga\n--------\nCow ghee 1 tsp"
        },
        {
          "Time": "09:00",
          "Activity": "Breakfast",
          "Comment": "Krithiga\n--------\nSoaked sprouts\nBadam - 10\nWalnut - 3\nPista - 4\nGround nut - 2 tsp\nPumpkin seeds - 1 tsp\nsunflower seed - 1 tsp\n\nHariprasad\n----------\nSoaked sprouts\nBadam - 10\nWalnut - 3\nPista - 4\nGround nut - 2 tsp\nPumpkin seeds - 1 tsp\n\nCommon\n------\nVegetable salad\nEgg"
        },
        {
          "Time": "10:00",
          "Activity": "Vegetable Juice",
          "Comment": "Common\n------\nKothavarai juice with 40 pieces\n1 glass each."
        },
        {
          "Time": "10:30",
          "Activity": "Medicinal Drink",
          "Comment": "Krithiga\n--------\nAvarampoo decoction - 1tsp in 1 glass\n\nHariprasad\n----------\nManjal karisalankanni decoction - 1tsp in 1 glass"
        },
        {
          "Time": "11:00",
          "Activity": "Detox Drink",
          "Comment": "Common\n------\nAmla and curry leaves juice with butter milk"
        },
        {
          "Time": "12:00",
          "Activity": "Lemon",
          "Comment": "Common\n------\nSmall lemon 1 each"
        },
        {
          "Time": "13:30",
          "Activity": "Lunch",
          "Comment": "Common\n------\nVazhapoo poriyal\nDrumstick"
        },
        {
          "Time": "13:45",
          "Activity": "Vegetable Raita",
          "Comment": "Common\n------\nRidge gourd\nAsh gourd\nBottle gourd\nSnake Gourd\nKovakkai\nChow-Chow"
        },
        {
          "Time": "15:30",
          "Activity": "Energy Drink",
          "Comment": "Krithiga\n--------\nHalf glass coconut milk"
        },
        {
          "Time": "17:00",
          "Activity": "Fruits",
          "Comment": "Common\n------\nAny fruits"
        },
        {
          "Time": "19:30",
          "Activity": "Tub bath",
          "Comment": "Krithiga\n--------\nTub bath with cold water"
        },
        {
          "Time": "19:45",
          "Activity": "Tub bath",
          "Comment": "Hariprasad\n----------\nTub bath with cold water"
        },
        {
          "Time": "20:00",
          "Activity": "Dinner",
          "Comment": "Common\n------\nTiffen"
        },
        {
          "Time": "20:45",
          "Activity": "Walking",
          "Comment": ""
        },
        {
          "Time": "20:55",
          "Activity": "Finisher Drink",
          "Comment": "Krithiga\n--------\nBadam pisin"
        },
        {
          "Time": "21:00",
          "Activity": "Prepare for next day",
          "Comment": "Common\n------\nSoak nuts\nOrder essentials\nSoak badam pisin"
        },
        {
          "Time": "21:15",
          "Activity": "Medicine",
          "Comment": "Hariprasad\n----------\nAshwaganda chooranam\nPaternia XT"
        }
      ]
    },
    {
      "Day": "Wednesday",
      "Schedule": [
        {
          "Time": "06:00",
          "Activity": "Drink Oil",
          "Comment": "Krithiga\n--------\nGingily oil 1 small tsp"
        },
        {
          "Time": "06:05",
          "Activity": "Yoga",
          "Comment": ""
        },
        {
          "Time": "07:00",
          "Activity": "Day starter vegetable",
          "Comment": "Hariprasad\n----------\nSmall Bitter gourd - 1"
        },
        {
          "Time": "08:00",
          "Activity": "Fruits",
          "Comment": "Common\n------\nHalf pomegranate each"
        },
        {
          "Time": "08:50",
          "Activity": "Drink Ghee",
          "Comment": "Krithiga\n--------\nCow ghee 1 tsp"
        },
        {
          "Time": "09:00",
          "Activity": "Breakfast",
          "Comment": "Krithiga\n--------\nSoaked sprouts\nBadam - 10\nWalnut - 3\nPista - 4\nGround nut - 2 tsp\nPumpkin seeds - 1 tsp\nsunflower seed - 1 tsp\n\nHariprasad\n----------\nSoaked sprouts\nBadam - 10\nWalnut - 3\nPista - 4\nGround nut - 2 tsp\nPumpkin seeds - 1 tsp"
        },
        {
          "Time": "10:00",
          "Activity": "Vegetable Juice",
          "Comment": "Common\n------\nKothavarai juice with 40 pieces\n1 glass each."
        },
        {
          "Time": "10:30",
          "Activity": "Medicinal Drink",
          "Comment": "Krithiga\n--------\nAvarampoo decoction - 1tsp in 1 glass\n\nHariprasad\n----------\nManjal karisalankanni decoction - 1tsp in 1 glass"
        },
        {
          "Time": "11:00",
          "Activity": "Detox Drink",
          "Comment": "Common\n------\nAmla and curry leaves juice with butter milk"
        },
        {
          "Time": "12:00",
          "Activity": "Lemon",
          "Comment": "Common\n------\nSmall lemon 1 each"
        },
        {
          "Time": "13:30",
          "Activity": "Lunch",
          "Comment": "Common\n------\nKeerai (manathakali)"
        },
        {
          "Time": "13:45",
          "Activity": "Vegetable Raita",
          "Comment": "Common\n------\nRidge gourd\nAsh gourd\nBottle gourd\nSnake Gourd\nKovakkai\nChow-Chow"
        },
        {
          "Time": "15:30",
          "Activity": "Energy Drink",
          "Comment": "Krithiga\n--------\nHalf glass coconut milk"
        },
        {
          "Time": "17:00",
          "Activity": "Fruits",
          "Comment": "Common\n------\nInclude Raw Guava / Athikkai"
        },
        {
          "Time": "19:30",
          "Activity": "Tub bath",
          "Comment": "Krithiga\n--------\nTub bath with cold water"
        },
        {
          "Time": "19:45",
          "Activity": "Tub bath",
          "Comment": "Hariprasad\n----------\nTub bath with cold water"
        },
        {
          "Time": "20:00",
          "Activity": "Dinner",
          "Comment": "Common\n------\nTiffen"
        },
        {
          "Time": "20:45",
          "Activity": "Walking",
          "Comment": ""
        },
        {
          "Time": "20:55",
          "Activity": "Finisher Drink",
          "Comment": "Krithiga\n--------\nBadam pisin"
        },
        {
          "Time": "21:00",
          "Activity": "Prepare for next day",
          "Comment": "Common\n------\nSoak nuts\nOrder essentials\nSoak badam pisin"
        },
        {
          "Time": "21:15",
          "Activity": "Medicine",
          "Comment": "Hariprasad\n----------\nAshwaganda chooranam\nPaternia XT"
        }
      ]
    }
  ]
}
